README.md
setup.py
ninklings/__init__.py
ninklings/__main__.py
ninklings.egg-info/PKG-INFO
ninklings.egg-info/SOURCES.txt
ninklings.egg-info/dependency_links.txt
ninklings.egg-info/entry_points.txt
ninklings.egg-info/not-zip-safe
ninklings.egg-info/requires.txt
ninklings.egg-info/top_level.txt