Metadata-Version: 1.0
Name: ninklings
Version: 0.1.1
Summary: Network ink enrichment stats
Home-page: https://github.ugent.be/cvneste/ninklings
Author: Christophe Van Neste
Author-email: christophe.vanneste@ugent.be
License: GNU GENERAL PUBLIC LICENSE
Platform: UNKNOWN
